MANIFEST.in
README.rst
setup.py
scripts/wipy_cli
wipy_tools/__init__.py
wipy_tools/package_metadata.json
wipy_tools/telnet.py
wipy_tools.egg-info/PKG-INFO
wipy_tools.egg-info/SOURCES.txt
wipy_tools.egg-info/dependency_links.txt
wipy_tools.egg-info/top_level.txt
wipy_tools.egg-info/zip-safe