Metadata-Version: 1.0
Name: wipy-tools
Version: 0.0.1
Summary: Control digital loggers web power switch
Home-page: https://github.com/dwighthubbard/wipy_tools/
Author: Dwight Hubbard
Author-email: dwight@dwighthubbard.com
License: MIT
Platform: UNKNOWN
